{"ocr_results":[{"text":"史料实录","box":[[162,67],[289,67],[289,90],[162,90]]},{"text":"破的大棒子你们举起来了。”大字报对叶林在“6.13”会上发言提出三个问","box":[[147,121],[879,119],[879,139],[147,141]]},{"text":"题，“据我们所知，教职工在9号前很少几个人反对校党委，他们怎么稀里糊","box":[[146,154],[879,152],[879,172],[146,174]]},{"text":"涂让上台发言的那个教师代表说出‘我们无限信赖工作组’这句极错误的话，","box":[[146,187],[878,185],[878,204],[146,206]]},{"text":"更令人气愤的是没有‘毛主席万岁’的口号。”","box":[[146,219],[580,218],[580,239],[146,240]]},{"text":"下午，叶林亲自来看大字报。","box":[[192,253],[459,253],[459,273],[192,273]]},{"text":"南京大学革命师生揪出反党反社会主义的现行反革命分子，前南京大学","box":[[190,285],[879,283],[879,304],[190,306]]},{"text":"校长匡亚明。","box":[[148,319],[263,319],[263,338],[148,338]]},{"text":"6月17日","box":[[146,370],[238,370],[238,391],[146,391]]},{"text":"校工作组办公室主持召开红五类子弟部分同学座谈会，鼓励他们积极参","box":[[189,402],[881,400],[881,423],[189,425]]},{"text":"加阶级斗争。","box":[[149,437],[266,437],[266,457],[149,457]]},{"text":"从15日起，学校里也出现了-一批批驳刘才堂、王铁成、大富的大字","box":[[190,468],[880,467],[880,488],[190,489]]},{"text":"报：【揭穿王铁成的真面目】、【应该相信毛主席派来的工作组】、【前大富、孟","box":[[147,502],[881,500],[881,521],[147,523]]},{"text":"家驹是左派吗？】等。","box":[[149,536],[343,536],[343,556],[149,556]]},{"text":"从早晨到第二天凌晨两点钟，北大校园里愤怒的学生群众到处围住黑帮","box":[[192,570],[880,567],[880,587],[192,590]]},{"text":"分子，高呼口号，揭露、控诉陆平黑帮罪恶。这时，工作组仍然采取不过问","box":[[148,602],[881,599],[881,620],[148,622]]},{"text":"的态度。","box":[[148,634],[222,634],[222,655],[148,655]]},{"text":"晚，中央人民广播电台广播了北京女三中给党中央和毛主席的公开信。","box":[[192,668],[852,666],[852,686],[192,688]]},{"text":"6月18日","box":[[148,720],[238,720],[238,740],[148,740]]},{"text":"《人民日报》发表社论【彻底搞好文化革命，彻底改革教育制度】。中共","box":[[192,752],[881,750],[881,771],[192,773]]},{"text":"中央和国务院宣布改革高考制度的决定，全校贴出许多拥护的大字报，各系","box":[[149,785],[881,784],[881,804],[149,805]]},{"text":"斗黑帮，游街现象少了。","box":[[150,819],[378,819],[378,839],[150,839]]},{"text":"国家主席刘少奇的夫人王光美到清华看大学报。","box":[[195,852],[635,852],[635,871],[195,871]]},{"text":"北大消息：","box":[[192,884],[289,884],[289,905],[192,905]]},{"text":"清晨5点，北大继续斗黑帮分子。这天的斗争，是十几天来群众中着","box":[[192,917],[882,916],[882,937],[192,938]]},{"text":"的怒火的总爆发，是这一阶段运动的最高峰。校园里人山人海，群众革命情","box":[[150,950],[882,949],[882,970],[150,971]]},{"text":"绪达到白热化程度。哲学楼、大饭厅、32楼、35楼、38楼、校医院、二院、","box":[[150,984],[882,984],[882,1003],[150,1003]]},{"text":"南阁，凡是有一块空场地的地方，拉来黑帮分子就斗。这一天北大校系两级","box":[[149,1016],[882,1015],[882,1035],[149,1036]]},{"text":"和学校附属各单位的黑帮分子、牛鬼蛇神统统被揪出来斗了（陆平、彭佩云","box":[[151,1049],[882,1049],[882,1069],[151,1069]]},{"text":"除外），有的黑帮分子一上午被斗了几次，群众愤怒到了极点，有的也狠狠地","box":[[150,1083],[882,1083],[882,1103],[150,1103]]},{"text":"揍了黑帮们几下。这天上午被斗的黑帮分子、牛鬼蛇神，据不完全的统计有","box":[[150,1116],[881,1116],[881,1135],[150,1135]]},{"text":"50多人。","box":[[148,1147],[230,1147],[230,1171],[148,1171]]},{"text":"中午11点多，北大工作组长张承先坐着小汽车满校园乱转。气势涵汹地","box":[[195,1182],[883,1182],[883,1202],[195,1202]]},{"text":"把革命师生赶回宿舍去“学习”、“讨论”，不许再斗争。","box":[[150,1214],[670,1214],[670,1234],[150,1234]]},{"text":"18","box":[[175,1266],[199,1266],[199,1288],[175,1288]]}],"dimensions":{"height":1334,"width":969}}