{"ocr_results":[{"text":"只见主席台上的朱成昭走到台沿边，举起右臂，向着台下的人群高声朗诵：","box":[[190,163],[995,163],[995,186],[190,186]]},{"text":"暮色苍茫看劲松，","box":[[528,206],[708,206],[708,227],[528,227]]},{"text":"乱云飞渡仍从容；","box":[[528,249],[708,249],[708,270],[528,270]]},{"text":"天生一个仙人洞，","box":[[528,290],[709,290],[709,311],[528,311]]},{"text":"无限风光在险峰！","box":[[528,332],[709,331],[709,352],[528,353]]},{"text":"在他念最后一句时，台下的东方红同学们不约而同地伴着他的节奏齐声朗诵","box":[[241,373],[1060,374],[1060,395],[241,394]]},{"text":"起来。","box":[[187,413],[252,413],[252,438],[187,438]]},{"text":"“斗批改”们又唱起“老子反动儿混蛋”、“滚他妈的蛋”等“红卫兵战歌”。","box":[[248,453],[1060,455],[1060,479],[248,477]]},{"text":"东方红的同学们坐在凳子上，不慌不乱，一遍又一遍地齐声朗读毛主席语录：","box":[[242,499],[1058,499],[1058,519],[242,519]]},{"text":"“下定决心，不怕牺牲，排除万难，去争取胜利！”","box":[[200,538],[738,538],[738,561],[200,561]]},{"text":"可能是经过调停，台上又恢复了平静。代表“东方红”发言的一位水文系女","box":[[242,582],[1059,582],[1059,602],[242,602]]},{"text":"同学讲述受工作队迫害情景时，声泪俱下，泣不成声，包括“斗批改”在内的全","box":[[190,623],[1061,623],[1061,646],[190,646]]},{"text":"场人员都为之动容。一位同学发言说，他是“红五类”出身，因为给工作队提意","box":[[190,665],[1060,665],[1060,685],[190,685]]},{"text":"见也被打成反革命。还有人发言，说他既不是“东方红”也不是“斗批改”，但看","box":[[191,708],[1060,708],[1060,728],[191,728]]},{"text":"到今天辩论会上“东方红”不卑不亢，纪律严明，所以决定加入东方红。许多外","box":[[191,749],[1060,749],[1060,769],[191,769]]},{"text":"校和外地旁听辩论会的人，也上台谴责“斗批改”横蛮无理，扰乱会场，支持“东","box":[[190,790],[1060,790],[1060,810],[190,810]]},{"text":"方红”并要求加入“东方红”。甚至有“斗批改”的成员，当场表示退出“斗批改”，","box":[[190,832],[1046,832],[1046,852],[190,852]]},{"text":"参加“东方红”。之后，台上的发言和台下人群的情绪几乎是一边倒，“斗批改”","box":[[191,874],[1050,874],[1050,894],[191,894]]},{"text":"已无招架之力。辩论会以“东方红”的胜利告终。","box":[[191,915],[723,914],[723,935],[191,936]]},{"text":"此时已是25日黎明，东方露出一线曙光。田春林站在主席台前，面向再再升","box":[[241,958],[1059,958],[1059,978],[241,978]]},{"text":"起的红日，挥动双手，指挥大家唱起了《东方红》。","box":[[190,999],[735,999],[735,1019],[190,1019]]},{"text":"起初，我们一直认为工作队的问题属于人民内部矛盾，邹家尤还是革命同志，","box":[[239,1037],[1045,1038],[1045,1061],[239,1060]]},{"text":"并不想一棍子将他打死。可是在8·24大辩论之后，何长工、邹家尤等依然抱成","box":[[191,1082],[1060,1082],[1060,1102],[191,1102]]},{"text":"一团，与“东方红”死磕到底。“东方红”因此提高了批判的调子，决心将他们拉","box":[[189,1124],[1060,1124],[1060,1144],[189,1144]]},{"text":"下马。","box":[[189,1163],[251,1163],[251,1188],[189,1188]]},{"text":"“东方红”因此又二进、三进、四进地质部。其间曾把邹家尤揪到地院，但","box":[[248,1205],[1060,1206],[1060,1229],[248,1228]]},{"text":"又给“斗批改兵团”抢了回去。后来“东方红”联合地质部机关的造反派，抓住","box":[[191,1249],[1060,1249],[1060,1269],[191,1269]]},{"text":"何长工长征时期曾在张国焘的“伪中央”当过“组织部长”、邹家尤参加过国民党","box":[[191,1290],[1059,1290],[1059,1310],[191,1310]]},{"text":"“蓝衣社”特务组织的辫子，将他们作为“三反分子”和“国民党特务”揪了出","box":[[197,1329],[1060,1330],[1060,1353],[197,1352]]},{"text":"来。何、邹的这些罪名在毛泽东仙逝后，自然也就像刘少奇“叛徒、内奸、工贼”","box":[[190,1374],[1049,1374],[1049,1394],[190,1394]]},{"text":"的罪名一样，获得平反。","box":[[190,1415],[449,1415],[449,1435],[190,1435]]},{"text":"东方红公社成立后的主要活动，就是四进地质部。当时公社总部人员大多都","box":[[241,1457],[1061,1457],[1061,1477],[241,1477]]},{"text":"在地质部“前线”上，我独自留守办公室，对现场情况不甚了解，只留下亲身所","box":[[191,1499],[1060,1499],[1060,1519],[191,1519]]},{"text":"见不完整的片断记忆。","box":[[192,1540],[422,1540],[422,1561],[192,1561]]},{"text":"91","box":[[613,1609],[636,1609],[636,1631],[613,1631]]}],"dimensions":{"height":1754,"width":1241}}