{"ocr_results":[{"text":"序二","box":[[552,157],[699,157],[699,211],[552,211]]},{"text":"北京地院文革的几个特点","box":[[380,247],[873,247],[873,281],[380,281]]},{"text":"阎长贵","box":[[577,312],[675,312],[675,349],[577,349]]},{"text":"北京地质学院文革回忆录出版了！我表示诚挚的热烈的祝贺！","box":[[209,446],[974,447],[973,474],[209,473]]},{"text":"文革时期我作为中央文革小组办公室的工作人员，和地质学院的人接触","box":[[211,514],[1102,514],[1102,538],[211,538]]},{"text":"较多，也了解得比较深，他们的红卫兵组织（地院东方红）的两代领导人朱","box":[[151,579],[1102,579],[1102,603],[151,603]]},{"text":"成昭、王大宾我都交往较多，很熟。当朱成昭在位时，我曾奉中央文革小组","box":[[152,642],[1103,643],[1103,670],[152,669]]},{"text":"某成员之命，去找朱成昭布置他们到四川去揪三线建设副总指挥彭德怀。但","box":[[152,708],[1104,709],[1104,735],[152,734]]},{"text":"当朱成昭对中央文革小组不满，有对立情绪时，我还几次登门劝他；当朱成","box":[[155,774],[1104,774],[1104,798],[155,798]]},{"text":"昭认真地躺倒不干时，我几次到医院找王大宾动员他挑起地院东方红的担子，","box":[[153,838],[1113,840],[1113,864],[153,862]]},{"text":"跟他说：“地院东方红是个有影响的群众组织，朱成昭倒了，‘东方红不能倒”！","box":[[151,903],[1112,902],[1112,929],[151,930]]},{"text":"直到现在，我和原地质学院的不少同志仍有交往，还有聚会畅叙。所以，听","box":[[152,968],[1104,968],[1104,995],[152,995]]},{"text":"到地质学院文革回忆录的编辑和出版非常高兴，恨不能很快读到一一而我这","box":[[152,1032],[1103,1032],[1103,1059],[152,1059]]},{"text":"个愿望很快就能实现了！","box":[[152,1096],[450,1098],[449,1126],[152,1124]]},{"text":"关于地质学院的文革，我觉得有这样几个特点。","box":[[211,1228],[798,1228],[798,1255],[211,1255]]},{"text":"第一，地质学院造反派保护院领导。","box":[[209,1294],[655,1294],[655,1320],[209,1320]]},{"text":"地院造反派无疑也做过错事，有不少“左”的东西，如批斗地质部、地","box":[[210,1359],[1103,1359],[1103,1383],[210,1383]]},{"text":"质学院的所谓走资派，降低所谓“反动学术权威”的高薪（把有人345元降","box":[[151,1422],[1103,1421],[1103,1448],[151,1449]]},{"text":"低到31元，287元降低到67元.：），以及参加社会上的一些造反活动等，","box":[[153,1489],[1100,1489],[1100,1513],[153,1513]]},{"text":"掌权后也有压制和听不得不同意见的情况等，有很多经验教训需要记取，也","box":[[153,1554],[1103,1554],[1103,1578],[153,1578]]}],"dimensions":{"height":1754,"width":1241}}