{"ocr_results":[{"text":"区、上海警备区和广州警备区都打了招呼，要他们一旦发现这几个人即刻请回北","box":[[189,176],[1059,176],[1059,200],[189,200]]},{"text":"京。广州警备司令部立刻派出侦察人员，守在火车站口，守株待兔。","box":[[189,229],[921,229],[921,252],[189,252]]},{"text":"所幸的是，朱成昭、梅建明五人在前一站下了火车。到广州后，他们联系上","box":[[241,282],[1059,281],[1059,302],[241,303]]},{"text":"叶向真和蒋良朴。一行人去广州西樵山、佛山坑了两大，打算回广州落脚到张华","box":[[191,334],[1060,334],[1060,357],[191,357]]},{"text":"府的姑姑家，但刚到不到半小时，广州警备司令部的人就到了。张华府的姑父和","box":[[191,386],[1059,386],[1059,409],[191,409]]},{"text":"姑姑都是中南局的十部，早就被打了招呼。","box":[[190,438],[646,438],[646,460],[190,460]]},{"text":"据梅建明所知，抓叶向真时，“中央文革”征求叶剑英的意见，当时处境困","box":[[241,489],[1059,489],[1059,512],[241,512]]},{"text":"难的叶师说：你们抓吧，抓谁我都不管。据叶向真后来回忆，江青早就想抓她，","box":[[191,541],[1044,541],[1044,564],[191,564]]},{"text":"因为她太活跃了。但抓她的主要目的，还是为了搞倒父亲。她出狱后才知道，为","box":[[190,594],[1059,594],[1059,618],[190,618]]},{"text":"了整叶剑英的材料，当时叶家的6个子女和保姆都被抓进了监狱。","box":[[192,647],[896,647],[896,670],[192,670]]},{"text":"儿个人被很客气地逮起来，送到从化疗养院，好吃好喝地款待，等待中央来","box":[[242,699],[1059,699],[1059,722],[242,722]]},{"text":"人带他们回北京。梅建明觉得，一来这跟周恩来“请他们回北京”的指示有关，","box":[[191,750],[1044,750],[1044,773],[191,773]]},{"text":"二来是因为叶家在当地的影响力。","box":[[190,802],[545,802],[545,825],[190,825]]},{"text":"过了一天，公安部副部长于桑从北京赶来，与朱成昭、叶向真单独谈话。朱、","box":[[239,854],[1047,853],[1047,877],[239,878]]},{"text":"叶二人一口咬定，来广州只是为躲避“中央文革”的批斗，出来散心。于桑将二","box":[[192,907],[1060,907],[1060,930],[192,930]]},{"text":"人带回了北京。","box":[[191,958],[349,958],[349,982],[191,982]]},{"text":"蒋良朴三人由广州警备司令部送回北京。梅建明由哥哥梅向明接回京。彼时，","box":[[239,1010],[1044,1009],[1044,1032],[239,1033]]},{"text":"其父梅龚彬已被逮捕，以“特务”之名关进了秦城监狱。","box":[[190,1062],[797,1062],[797,1085],[190,1085]]},{"text":"1967年11月初，正在外地串联的梅建明接到电话通知，回校复课闹革命。","box":[[241,1114],[1041,1114],[1041,1138],[241,1138]]},{"text":"一回校，他就被看押起来。朱成昭专案组的工作人员宣布，对其实行隔离审查。","box":[[192,1166],[1046,1166],[1046,1189],[192,1189]]},{"text":"朱成昭专案组由中央专案组“二办”负责。让梅建明交代的问题有三：攻击","box":[[241,1220],[1059,1220],[1059,1243],[241,1243]]},{"text":"无产阶级司令部；叛逃国外；冲击中南海，谋害毛泽东。","box":[[191,1272],[798,1272],[798,1295],[191,1295]]},{"text":"第三条事出有因。大约在1967年8月，朱成昭、叶向真、蒋良朴等人在颐和","box":[[241,1323],[1060,1323],[1060,1346],[241,1346]]},{"text":"园开会。有人提出，直接去中南海见毛泽东，跟他谈“中央文革”的问题。若他","box":[[190,1375],[1060,1375],[1060,1398],[190,1398]]},{"text":"不知道“中央文革”的行径，就提醒他；如果他知道并支持，不如动员老师们起","box":[[191,1427],[1060,1427],[1060,1450],[191,1450]]},{"text":"来废掉江青。但这次会梅建明因事并未参加，只是会后听他们谈起过。他只坦白","box":[[190,1479],[1060,1479],[1060,1502],[190,1502]]},{"text":"承认第一条，让专案组的人非常恼怒。","box":[[190,1530],[596,1531],[596,1555],[190,1554]]},{"text":"277","box":[[609,1609],[641,1609],[641,1633],[609,1633]]}],"dimensions":{"height":1754,"width":1241}}