{"ocr_results":[{"text":"就又躺倒在床上睡下。几个同学先后起床，都来问我：队长，怎么办？起来呀！","box":[[191,164],[1048,164],[1048,184],[191,184]]},{"text":"我只好起来，洗一把冷水脸，说：大家说，怎么办？走！我们不停步！我们长征","box":[[189,212],[1060,211],[1060,234],[189,235]]},{"text":"去！","box":[[187,258],[228,258],[228,287],[187,287]]},{"text":"终于，我们八个同学（六个男生，两个女生）决定立刻出发，在中央停止串","box":[[238,310],[1060,310],[1060,333],[238,333]]},{"text":"联的文件下发之前，走出去（附：长征队出发前的照片）。后来我们由于种种原因，","box":[[189,358],[1045,358],[1045,381],[189,381]]},{"text":"仅走了从贵州的遵义徒步长征走到重庆，行程1000华里，长征途中我们得到","box":[[190,408],[1061,408],[1061,431],[190,431]]},{"text":"了锻炼，学到了不少知识。不在话下。","box":[[192,456],[598,456],[598,479],[192,479]]},{"text":"北京地贸学院东为仁公社","box":[[530,857],[684,842],[687,870],[533,885]]},{"text":"長征队","box":[[550,897],[672,887],[675,926],[553,936]]},{"text":"建安——井肉山","box":[[568,946],[642,943],[643,961],[568,964]]},{"text":"红卫兵长征队出发前在林天民家的合影","box":[[373,993],[706,993],[706,1013],[373,1013]]},{"text":"红卫兵长征队出发前在林天民家的合影","box":[[345,1065],[766,1065],[766,1088],[345,1088]]},{"text":"地质东方红长征队与当年摆渡红军的老躺公合影","box":[[342,1467],[749,1467],[749,1490],[342,1490]]},{"text":"地质东方红长征队与当年摆渡红军的老崩公合影","box":[[302,1554],[823,1554],[823,1577],[302,1577]]},{"text":"339","box":[[608,1608],[642,1608],[642,1631],[608,1631]]}],"dimensions":{"height":1754,"width":1241}}