{"ocr_results":[{"text":"要看病，要走十几里才能到殷家汇诊所，小学的同学们就主动扶我到医院","box":[[241,156],[1061,156],[1061,179],[241,179]]},{"text":"看病。","box":[[188,204],[251,204],[251,230],[188,230]]},{"text":"需要热水，队上的家属就轮流给我送热水，倒脏水。我经常被她们请去做客，","box":[[240,271],[1045,270],[1045,293],[240,294]]},{"text":"帮我改善生活，有时候也谈谈家常。她们都是有好几个孩子的妈妈，在文化大革","box":[[191,319],[1060,319],[1060,342],[191,342]]},{"text":"命初期，这些家属也参加到了群众组织中，同职工一起组织毛泽东思想文艺宣传","box":[[190,367],[1060,368],[1060,391],[190,390]]},{"text":"队，到各地巡回演出。由于有这个历史原因，这个队的家属革命委员会也是一级","box":[[191,417],[1060,418],[1060,439],[191,437]]},{"text":"组织，在全队很有威信，受大队工会直接领导。我记得家属革委会主任姓马，是","box":[[190,464],[1061,464],[1061,487],[190,487]]},{"text":"一个热心快肠，高度负责的人。她在一个节目中演地主，十分逼真。还有一位我","box":[[189,513],[1061,514],[1061,537],[189,536]]},{"text":"的湖北老乡，叫陈香桃，两个孩子的妈妈，丈夫也是湖北武汉人，是一个机长。","box":[[190,561],[1047,561],[1047,584],[190,584]]},{"text":"由于老乡的关系，她总是照顾我。我由于腿伤回武汉探亲，她还委托我带上她当","box":[[192,612],[1059,612],[1059,632],[192,632]]},{"text":"时九岁的大女儿随行，带去见她的爷爷奶奶。我受到了近十多个家属大姐的照顾，","box":[[190,660],[1042,660],[1042,683],[190,683]]},{"text":"心中有说不尽得感激。","box":[[192,710],[420,710],[420,731],[192,731]]},{"text":"不仅如此，她们还力所能及地帮助我们。她们想方设法寻找我们同学的脏衣","box":[[242,774],[1059,774],[1059,794],[242,794]]},{"text":"服，经常帮我们洗干净，缝补好。每每有脏衣服，我总是藏起来，但又经常被她","box":[[190,822],[1060,822],[1060,845],[190,845]]},{"text":"们找到，很过意不去。有一次，她们竟到百十余里外的野外，帮我们的同学洗被","box":[[191,871],[1058,871],[1058,891],[191,891]]},{"text":"子、蚊帐和脏衣服，还帮我们做了一顿香甜可口的饭菜。我们的同学都说，这是","box":[[192,920],[1059,920],[1059,940],[192,940]]},{"text":"托你的福，你帮她们编排节目的搞劳。是啊！将心比心，她们都是大姐姐辈的。","box":[[190,969],[1046,968],[1046,989],[190,990]]},{"text":"我没有姐姐，在324队体会到了大姐姐的关心、照顾和温暖。","box":[[191,1018],[845,1018],[845,1037],[191,1037]]},{"text":"毕业分配各奔东西","box":[[243,1082],[436,1082],[436,1103],[243,1103]]},{"text":"在我们返回大队部准备毕业分配的那几个星期里，我们还常常成群结队的到","box":[[241,1146],[1061,1146],[1061,1169],[241,1169]]},{"text":"离大队部三里地的殷家河去游泳。我记得殷家河上架了一座公路桥，可以走汽车。","box":[[190,1195],[1047,1195],[1047,1218],[190,1218]]},{"text":"桥下就是一片天然的露天游泳场，还受不到太阳的暴晒。每天中午和晚饭后，大","box":[[189,1243],[1061,1243],[1061,1266],[189,1266]]},{"text":"家都到那里去享受大自然的洗涤。她洗涤了我们将近一年的疲劳，也洗涤了我们","box":[[191,1293],[1058,1293],[1058,1313],[191,1313]]},{"text":"日益滋生的消极情绪，注进我们心田的是对毕业以后的期盼！","box":[[192,1341],[848,1341],[848,1364],[192,1364]]},{"text":"就在宣布毕业方案的那儿大，我们班十分的宝贵的女同学们都找到了自己的","box":[[242,1407],[1059,1407],[1059,1427],[242,1427]]},{"text":"另一半。可事先一点风声也没有，可谓神秘、神速。其主要原因是因为女同学独","box":[[191,1454],[1061,1454],[1061,1477],[191,1477]]},{"text":"自一人到社会上非常紧张，还不如找一个知根知底的老同学。我不记得我当时是","box":[[193,1503],[1060,1503],[1060,1526],[193,1526]]},{"text":"什么学生干部，基本上协助军、工宣队和老师做了不少组织工作。我由于现在的","box":[[189,1551],[1060,1551],[1060,1574],[189,1574]]},{"text":"368","box":[[611,1610],[640,1610],[640,1631],[611,1631]]}],"dimensions":{"height":1754,"width":1241}}