{"ocr_results":[{"text":"504平定縣狸不平定：山西省平定縣文革史","box":[[35,53],[245,53],[245,67],[35,67]]},{"text":"動许多人，對文革已经心灰意冷。這時全縣開始大瓣學曾班，李守珍在","box":[[68,119],[513,119],[513,133],[68,133]]},{"text":"縣委常委會上被批判·在全縣文衛系统集中召開的大會上·超岐山揪出来","box":[[67,144],[514,144],[514,158],[67,158]]},{"text":"了。我在剧围被批门，縣委書记左治負和我谈話，為我是好人，决定在","box":[[69,170],[514,170],[514,183],[69,183]]},{"text":"单位拟門，不在系统门。我住在单位，房子裡都贴满大字報，冬天揪门","box":[[69,195],[514,195],[514,207],[69,207]]},{"text":"時·先放我在火墟旁，大家图攻，我出一身子汗，衣服也濕透了，然後","box":[[68,219],[513,219],[513,232],[68,232]]},{"text":"馬上揪到院裡在門，衣服馬上结了冰，你冻得登料。有時又把我揪到系","box":[[68,244],[512,244],[512,257],[68,257]]},{"text":"统·門了次。","box":[[66,269],[161,269],[161,282],[66,282]]},{"text":"縣级幹部是门梁志铭和劉志義。這些都是红總站的人了。這一段我們","box":[[96,295],[515,295],[515,308],[96,308]]},{"text":"集中住单位，老婆去食堂打低，人家给我打病號。大家為我是一個好","box":[[69,319],[514,319],[514,333],[69,333]]},{"text":"人。","box":[[67,344],[92,344],[92,358],[67,358]]},{"text":"「一打三反」、「清隧」，大概是四五個月的時間。然後是「揭、批、","box":[[91,365],[511,367],[511,384],[91,382]]},{"text":"改了·進入了改的段。我近乎變成反革命，帽子拿在群累手中，隨時可","box":[[68,394],[514,394],[514,408],[68,408]]},{"text":"以给我戴上了。但軍代表说：你定性不是反革命，你藝街還行，别人也","box":[[68,419],[514,419],[514,433],[68,433]]},{"text":"替不了你，縣裡要搞剧围·你就留在剧围吧！」而原来剧围的人，全部下","box":[[68,444],[512,444],[512,458],[68,458]]},{"text":"放到了二輕系统當工人去了，我的老婆分配到了燈頭廠去劳勤改造去了。","box":[[67,470],[508,470],[508,482],[67,482]]},{"text":"到後來，我上了壹，才又把剧围的人都调回来。當時剧围的書記是李","box":[[95,494],[514,494],[514,507],[95,507]]},{"text":"有全，这是個好書記。有政治见解，特别對文革有自己的看法，然而他又","box":[[68,519],[514,519],[514,532],[68,532]]},{"text":"没有明顯的派性。他和我经遍次深刻的谈話，後来我才員轉了正，當","box":[[68,544],[514,544],[514,557],[68,557]]},{"text":"了剧围的副書記。","box":[[69,569],[174,569],[174,583],[69,583]]},{"text":"【访谈者問：當時批你是什展罪名？]我是红總站的頭頭，什展罪名","box":[[99,595],[513,595],[513,608],[99,608]]},{"text":"由人说。這時把三代會」和剧围合供，然後排樣板，排不下去。王治","box":[[69,618],[512,618],[512,631],[69,631]]},{"text":"魁問我怎辨？我说要新招一批人，基本功抓起，把三代會」這些","box":[[67,643],[514,643],[514,657],[67,657]]},{"text":"「白毛」分配出去·调一部分老人回剧图来。所以縣视才在70年招了十","box":[[65,665],[515,667],[515,684],[65,682]]},{"text":"個人。這時我主要精力是抓70班了。後来70班排了《沙家浜》，到普中","box":[[69,694],[514,694],[514,708],[69,708]]},{"text":"會演，一炮打馨。後來，我到文化馆，当馆长，副科级。1984年10月離","box":[[69,719],[514,719],[514,733],[69,733]]}],"dimensions":{"height":826,"width":582}}