{"ocr_results":[{"text":"185","box":[[6006,520],[6137,520],[6137,600],[6006,600]]},{"text":"184","box":[[444,533],[566,533],[566,605],[444,605]]},{"text":"一葉知秋","box":[[2682,536],[3000,563],[2993,644],[2675,616]]},{"text":"第五章農志成城","box":[[3570,549],[4169,527],[4172,607],[3573,629]]},{"text":"文革的本義上，把對人們的「靈魂革命」與「肉體革命」統一起","box":[[442,768],[2993,789],[2992,885],[442,864]]},{"text":"理及社會舆的層面上，形成某種群性的思潮。文革群累組","box":[[3579,781],[6127,766],[6127,853],[3579,869]]},{"text":"來了，而且「靈魂革命」的激烈舆「肉體革命」的残酷是成正比","box":[[445,918],[2987,939],[2987,1027],[444,1006]]},{"text":"織的思潮取向使不同層的文革群對於複雜多變的文革形勢","box":[[3581,934],[6121,918],[6122,998],[3582,1014]]},{"text":"的。值得注意的是，文革雨派群往往為了配合文革形勢以及","box":[[448,1068],[2988,1092],[2987,1177],[447,1153]]},{"text":"做出自已所特有的判和反應，成為一條顯現文革群累運動演","box":[[3581,1081],[6129,1066],[6130,1154],[3582,1169]]},{"text":"自己任務的需要，在不同地點和場合而共同探用暴力行径來對","box":[[453,1218],[2987,1239],[2987,1327],[452,1306]]},{"text":"變的丶來自群之中的重要線索·思潮取向比起其他取向顯得","box":[[3581,1231],[6124,1218],[6125,1304],[3582,1317]]},{"text":"付同樣的一些文革對象人物等。","box":[[447,1374],[1742,1376],[1742,1456],[447,1454]]},{"text":"格外醒目和重要，因為它是指導和制約文革群組織生存和行","box":[[3581,1384],[6122,1371],[6122,1448],[3582,1462]]},{"text":"這種取向的第二點是文革群組織之間的爭和約不伯","box":[[618,1521],[2977,1545],[2976,1622],[617,1598]]},{"text":"為的一个「視窗」·文革當中的群思潮就其數量難以統計，就","box":[[3581,1534],[6129,1521],[6130,1599],[3582,1612]]},{"text":"導致兵戎相見，大動干戈，而且文革群雨派都曾將有暴力","box":[[447,1673],[2985,1695],[2984,1772],[447,1751]]},{"text":"其類型約有十種左右，就群組織的思潮而言可分為四種：","box":[[3579,1684],[6106,1668],[6106,1749],[3579,1764]]},{"text":"的手段來使暴力取向升级為群累性的武国·群累武开的尖锐、","box":[[447,1824],[2982,1845],[2982,1914],[447,1893]]},{"text":"造反派思潮和保守派思潮，激進的、極端的造反派思潮和保守","box":[[3582,1832],[6124,1821],[6125,1901],[3582,1912]]},{"text":"激烈、残酷和兒狠，可前述清華百日大武們略见-斑·愈是","box":[[442,1971],[2982,1989],[2982,2070],[442,2051]]},{"text":"的、温和的造反派思潮·這些思潮萌發於毛澤東的文革思想，","box":[[3582,1982],[6104,1974],[6104,2051],[3582,2059]]},{"text":"到了文革群組織的晚期，其暴力取向愈發不可收拾，以致暴","box":[[440,2124],[2977,2142],[2977,2220],[439,2201]]},{"text":"生長於文革的實践之中，但是任何一個群性文革思潮都不等","box":[[3579,2134],[6127,2124],[6127,2201],[3579,2212]]},{"text":"力取向在群武开中達到了無所不用其極的程度。這種暴力取","box":[[442,2271],[2975,2292],[2974,2370],[442,2349]]},{"text":"同於毛澤東的文革思想，都與文革理和文革實之間有一定","box":[[3579,2282],[6127,2274],[6127,2351],[3579,2359]]},{"text":"向管具有單位的或地區的特微，但它對包括文革群在内的","box":[[440,2421],[2975,2442],[2974,2517],[439,2496]]},{"text":"的差巽、偏離甚至「修正」·實際上，文革群思潮的廣泛而又","box":[[3584,2434],[6119,2424],[6119,2494],[3584,2504]]},{"text":"無數受害者乃至施害者的内心創傷乎是無法治愈的。在北京","box":[[440,2568],[2980,2590],[2979,2667],[439,2646]]},{"text":"深刻的不同恰恰表明了文革群累運動的演變及分化。","box":[[3587,2584],[5742,2576],[5742,2646],[3587,2654]]},{"text":"大學校百年之際，年已耄的著名學者季羡林先生出版的《牛","box":[[437,2719],[2975,2737],[2974,2817],[437,2799]]},{"text":"印红標先生把文革初期最引人注目的群思潮概括為|老紅","box":[[3770,2734],[6129,2724],[6130,2794],[3770,2804]]},{"text":"棚雜記》一書，以作者的親身經歷控了這種暴力取向，給我們","box":[[437,2869],[2975,2887],[2974,2965],[437,2946]]},{"text":"衛兵思潮和造反派紅衛兵思潮」·在我看來，這雨個思潮大致上","box":[[3584,2882],[6122,2871],[6122,2944],[3584,2954]]},{"text":"後人永遠防止這種暴力取向的死灰復燃樹立起一座不朽的警鐘！","box":[[440,3021],[2949,3042],[2948,3112],[439,3091]]},{"text":"分别代表了流行於文革最早的四、五個月和1967年前七个月這","box":[[3584,3027],[6129,3021],[6130,3099],[3584,3104]]},{"text":"在文革研究中，人們往往會把暴力與武混同，管二者","box":[[603,3169],[2975,3187],[2974,3265],[602,3246]]},{"text":"雨個不同段的造反派思潮。下面我將大段引用印红標先生的","box":[[3589,3179],[6124,3171],[6124,3241],[3590,3249]]},{"text":"有著不可分割的關係·這裹要指出的是，暴力及其取向是單向","box":[[432,3316],[2967,3335],[2966,3415],[431,3396]]},{"text":"概述。","box":[[3585,3318],[3864,3325],[3862,3407],[3584,3401]]},{"text":"性的、非交互性的，而武开则是雙向性的、交互性的，因為前","box":[[434,3466],[2972,3482],[2971,3560],[434,3544]]},{"text":"【老红衛兵思潮直接承【文革】前的「级們爭為』的理","box":[[3760,3479],[6127,3469],[6127,3539],[3760,3549]]},{"text":"者更多是指文革群組織對文革對象個人的迫害和對社會的","box":[[421,3616],[2969,3629],[2969,3707],[421,3694]]},{"text":"·在社會分析方面，它為：中國資本主義復辟的主要危","box":[[3584,3616],[6130,3614],[6130,3694],[3584,3697]]},{"text":"害而言，而後者主要是指雨個截然對峙的群組織之間的暴力","box":[[429,3761],[2967,3777],[2966,3860],[429,3844]]},{"text":"來自『地主、資產級及其知識份子』，為數不多的走資派是間","box":[[3584,3766],[6130,3764],[6130,3844],[3584,3847]]},{"text":"之。總之，在一定意義上可以，正是暴力取向以及武們導","box":[[427,3909],[2985,3922],[2984,4007],[426,3994]]},{"text":"級人在内的代理人，資本主義復辟的典型構想是回到1949","box":[[3584,3914],[6132,3914],[6132,3999],[3584,3999]]},{"text":"致了文革群組織的不同衰败和共同消解。","box":[[427,4059],[2202,4072],[2201,4147],[426,4134]]},{"text":"年之前的舊中國，是原來的地主、資產級、國民黛捲土重來。","box":[[3587,4061],[6109,4056],[6109,4136],[3587,4142]]},{"text":"因而，文革打撃的重點在『地主丶資產隋級及其知識份子』、一","box":[[3579,4201],[6121,4183],[6122,4289],[3580,4307]]},{"text":"十、文革群組織的思潮取向","box":[[429,4317],[1631,4325],[1630,4406],[429,4397]]},{"text":"小攝走資派。這種思潮指導下的行動是『破四舊』丶批判文化教","box":[[3587,4354],[6132,4348],[6132,4436],[3587,4442]]},{"text":"每一文革群組織大都有自己的觀點和見解。這些反映亚","box":[[590,4493],[2964,4509],[2964,4597],[589,4581]]},{"text":"育路線丶知識界人士丶文教界及北京市委『包庇資產級分子』","box":[[3584,4501],[6140,4501],[6140,4586],[3584,4586]]},{"text":"體現某一群組織利益與要求的觀點和見解的總和，在社會心","box":[[424,4643],[2962,4656],[2961,4744],[424,4731]]},{"text":"的導幹部。老紅衛兵的們爭偏重外，偏重『隋級人』、『反","box":[[3589,4646],[6132,4646],[6132,4731],[3589,4731]]}],"dimensions":{"height":5215,"width":6450}}