{"ocr_results":[{"text":"办学理念","box":[[188,162],[287,162],[287,186],[188,186]]},{"text":"高元贵特别强调学习苏联要注意结合中国实际，不可盲目照搬，在向苏联专","box":[[241,213],[1050,213],[1050,236],[241,236]]},{"text":"家学习的基础上，要结合中国地质工作的特点和实际需要进行教学改革。20世","box":[[191,263],[1041,263],[1041,283],[191,283]]},{"text":"纪60年代前期，高元贵领导全校教师结合中国实际对学校的专业设置、教学计","box":[[190,313],[1046,313],[1046,333],[190,333]]},{"text":"划、教学大纲、教学方法等都进行了改革，组织教师编写出了一批中国自已的地","box":[[190,361],[1049,361],[1049,381],[190,381]]},{"text":"质专业课程教材。","box":[[191,410],[372,410],[372,431],[191,431]]},{"text":"学校教学","box":[[189,456],[287,456],[287,481],[189,481]]},{"text":"高元贵在由革命者向教育家的角色转换的过程中，十分强调积极探索、大胆","box":[[242,507],[1047,507],[1047,527],[242,527]]},{"text":"改革。1958年他调到北京地质学院后，经过认真的调查研究，提出了“要全面","box":[[191,556],[1041,556],[1041,576],[191,576]]},{"text":"贯彻党的教育方针，就要彻底地实行教学改革”的意见，经过学院党委常委扩大","box":[[191,605],[1047,605],[1047,625],[191,625]]},{"text":"会议讨论，作出了《关于教学改革的某些主要问题的原则决定》。随后，学校对","box":[[191,653],[1049,653],[1049,676],[191,676]]},{"text":"培养目标、学制、专业设置等都进行了改革。高元贵还着力于课程设置、教学内","box":[[189,702],[1049,702],[1049,725],[189,725]]},{"text":"容、教学方法的改革，他亲自组织领导了建立《综合地质基础》课程的工作，并","box":[[190,751],[1050,751],[1050,771],[190,771]]},{"text":"为这门课讲了第一节课一一序论。他强调要加强学生的“三基”训练，非常重视","box":[[192,800],[1050,800],[1050,820],[192,820]]},{"text":"抓好教学实习和生产实习这两个校外实践性教学环节，使之成为学校各教学环节","box":[[190,849],[1049,849],[1049,869],[190,869]]},{"text":"中的重头戏。他大力提倡在教学内容上做到“少而精”，在教学方法上搞“启发","box":[[189,896],[1051,897],[1051,920],[189,919]]},{"text":"式”，反对“填鸭式”，提倡“因材施教”，全面推进了学校教学领域的改革。","box":[[189,945],[1046,945],[1046,968],[189,968]]},{"text":"培养人才","box":[[188,993],[286,993],[286,1018],[188,1018]]},{"text":"高等学校的主要任务是为国家培养人才，高元贵十分重视遵照党的教育方针","box":[[242,1043],[1048,1043],[1048,1063],[242,1063]]},{"text":"把学生培养成为德智体全面发展的社会主义劳动者。","box":[[190,1091],[749,1091],[749,1114],[190,1114]]},{"text":"高元贵把德育放在对学生进行教育的首位，十分重视系统的马克思主义基础","box":[[242,1141],[1050,1141],[1050,1161],[242,1161]]},{"text":"理论教育，特别是哲学的教育。他也非常重视革命传统教育和形势政策教育，使","box":[[190,1190],[1050,1190],[1050,1210],[190,1210]]},{"text":"学生建立起正确的世界观和人生观。","box":[[191,1239],[571,1239],[571,1259],[191,1259]]},{"text":"在智育方面，他强调要按照教学和学习自身的规律办事。在当时“以阶级斗","box":[[241,1287],[1049,1287],[1049,1310],[241,1310]]},{"text":"争为纲”，政治“运动”频繁的大环境中，他号召学生要认真读书，并为之创造","box":[[191,1334],[1050,1334],[1050,1357],[191,1357]]},{"text":"安静的坏境，保证足够的时间，让学生坐下来刻苦钻研，真是难能可贵。","box":[[191,1385],[972,1385],[972,1405],[191,1405]]},{"text":"体育","box":[[187,1430],[238,1430],[238,1457],[187,1457]]},{"text":"高元贵十分重视体育工作，学校里学生和教职工的群众性体育活动蓬勃开","box":[[241,1483],[1034,1483],[1034,1503],[241,1503]]},{"text":"展，高校运动会上北京地质学院名列前茅，登山攀岩更是北京地质学院的特色项","box":[[191,1531],[1050,1531],[1050,1551],[191,1551]]},{"text":"172","box":[[607,1610],[636,1610],[636,1631],[607,1631]]}],"dimensions":{"height":1754,"width":1241}}