{"ocr_results":[{"text":"到了1962年以后，困难时期逐渐过去了。困难时期即便学校吃不好的话，","box":[[240,164],[1036,164],[1036,187],[240,187]]},{"text":"家里还有些特供，因为父亲是正部级干部，所以还有些特殊供应，甲级供应证。","box":[[190,214],[1046,213],[1046,234],[190,235]]},{"text":"每个礼拜六可以回家补一下，所以我在困难时期过得还可以。特别是在1961年，","box":[[189,261],[1036,262],[1036,285],[189,284]]},{"text":"因为每年我父亲可以有一次休养，我们那年到青岛去，那就是天天鱼呀肉啊的，","box":[[190,311],[1045,310],[1045,333],[190,334]]},{"text":"都是充分供应。专门配了一个厨师，你想吃什么就报，反正不用掏钱的，他去给","box":[[192,361],[1048,361],[1048,381],[192,381]]},{"text":"你买来，给你做好。大鱼大肉吃了一个月，我那一个假期下来长了十儿公分。所","box":[[192,410],[1048,410],[1048,430],[192,430]]},{"text":"以那个时候在这样的家庭中，待遇还是很高的。别人还吃不饱呢。当然，当时也","box":[[193,458],[1048,458],[1048,478],[193,478]]},{"text":"没有想到这么多了。反正就是说，我还有这样的待遇。","box":[[190,507],[771,506],[771,527],[190,528]]},{"text":"学校里管得非常严格的，基本上有点儿接近于军事化。因为这个学校从小学","box":[[242,556],[1049,556],[1049,576],[242,576]]},{"text":"到中学都是一样的。我们虽然住校，幼儿园里每个班都有阿姨，小学1-4年级的","box":[[191,605],[1050,605],[1050,625],[191,625]]},{"text":"时候，每个班都有生活老师，我们叫阿姨了，就是管你的生活：按时睡觉、起床、","box":[[191,654],[1036,654],[1036,674],[191,674]]},{"text":"洗澡，还要做一些劳动。那都是在监督下的，吃饭都是要排队去，每个桌10个","box":[[190,702],[1049,702],[1049,725],[190,725]]},{"text":"人，都有固定座位，不能乱坐，打饭分饭都是有规矩的。桌有桌长，宿舍有宿舍","box":[[190,749],[1050,749],[1050,772],[190,772]]},{"text":"长，班有班长，所以管理是很严的。每天真正的自由活动就是每天下午有一个半","box":[[190,798],[1050,798],[1050,821],[190,821]]},{"text":"小时。由于校园很大，里面有草坛，有很大的操场，所以说活动范围还是很大的。","box":[[192,849],[1035,849],[1035,869],[192,869]]},{"text":"自由活动时间可以踢足球，可以玩儿各种体育器械，像什么双扛、单扛、游泳等","box":[[193,898],[1050,898],[1050,918],[193,918]]},{"text":"等，各种各样的，那都是很好的条件。要不就到草坛里去玩儿捉迷藏，还有一些","box":[[191,946],[1050,946],[1050,966],[191,966]]},{"text":"小孩儿们的游戏，什么骑马打仗啊、撞撞拐了、打个瓦了，这都是随便的，在这","box":[[192,995],[1049,995],[1049,1015],[192,1015]]},{"text":"一个半钟头里头都可以玩儿，那是很自由的。","box":[[189,1040],[671,1041],[671,1065],[189,1064]]},{"text":"我们在孩童时代过的是一种很有趣的生活。虽然其它时间都是军事化，在","box":[[252,1091],[1052,1091],[1052,1114],[252,1114]]},{"text":"严格的管制下，但是稍微有一点儿空闲的话，总是需要发泄一下，所以就想出一","box":[[188,1138],[1050,1139],[1050,1162],[188,1161]]},{"text":"些鬼主意来。当时冬天要生火，生火就需要劈柴，这个劈柴堆得像山一样高，我","box":[[189,1186],[1052,1188],[1052,1212],[189,1210]]},{"text":"们那个时候刚三年级，三年级小孩子看到高高的劈柴堆，就觉得它像山一样。往","box":[[189,1236],[1051,1237],[1051,1260],[189,1259]]},{"text":"上爬也不容易，一边爬一边滑，觉得很有趣。外面吗，大家都看得见，总想找一","box":[[190,1286],[1050,1287],[1050,1310],[190,1309]]},{"text":"个别人都看不见的地方，就在劈柴堆里挖了一个洞，上头拿草席子给盖上，像一","box":[[191,1335],[1050,1335],[1050,1355],[191,1355]]},{"text":"个地窖似的，藏在里头讲故事。但是里头又太黑，太黑怎么办呢，就从草地里随","box":[[191,1384],[1049,1384],[1049,1404],[191,1404]]},{"text":"便抹了点儿草来，点火玩儿。这一点不要紧，把上面的芦苇席子给烧着了，这下","box":[[190,1432],[1049,1432],[1049,1455],[190,1455]]},{"text":"可吓坏了，大家拼命地跑。一下子大火冲大，劈柴堆吗，你想想，点起大火来，","box":[[193,1483],[1046,1483],[1046,1503],[193,1503]]},{"text":"那还有救啊！把这个劈柴堆烧了起来，劈柴好大的一堆呢。大概好儿万斤的劈柴","box":[[191,1531],[1050,1531],[1050,1551],[191,1551]]},{"text":"23","box":[[608,1609],[631,1609],[631,1632],[608,1632]]}],"dimensions":{"height":1754,"width":1241}}