{"ocr_results":[{"text":"/566／内蒙文革風雷—一位造反派领袖的口述史","box":[[192,58],[748,56],[748,81],[192,83]]},{"text":"1966年7、8月份，在“破四舊”属暴中，丙蒙師院揪出100多名批开目","box":[[93,163],[850,160],[850,181],[93,184]]},{"text":"標，力沙克也被揪回，通通進北门外原教師俱樂部。白天批门或強迫動；","box":[[43,208],[853,205],[853,226],[43,229]]},{"text":"晚間不准回家。由當時的工作組、工作除和新成立的院文革委會負责看押。","box":[[42,250],[853,247],[853,270],[42,273]]},{"text":"1966年11月，全國大串，師院派紅衛兵走了很多。“文革委會”無警","box":[[44,295],[852,293],[852,313],[44,315]]},{"text":"瓦解。接替“委會”管“黑除”的，是造反派的外語系英四學生姜振","box":[[44,340],[852,338],[852,358],[44,360]]},{"text":"華，他對力沙克比较関照。","box":[[44,384],[326,384],[326,404],[44,404]]},{"text":"一天下午’姜振華找到我，低聲：“力沙克想和你見一面。”“他有","box":[[90,425],[853,423],[853,447],[90,449]]},{"text":"什事？”我問。","box":[[45,471],[231,471],[231,492],[45,492]]},{"text":"“他想離開這裹，回上海。”姜振華又：“我和梅老師商量，力沙","box":[[107,514],[852,513],[852,534],[107,535]]},{"text":"克在那裹等著，你去和他谈谈吧，已經要求次了。”","box":[[44,557],[612,554],[612,578],[44,581]]},{"text":"梅青由是我大學老，人正道。文革中和我一起参舆造反，他的妻子","box":[[93,603],[852,603],[852,623],[93,623]]},{"text":"是系秘書。當晚，我在梅老師家見到力沙克。","box":[[46,646],[520,646],[520,666],[46,666]]},{"text":"力满，很削瘦，穿件破舊的棉軍衣，一雙舊皮鞋，身上的傲氣少","box":[[94,690],[851,690],[851,710],[94,710]]},{"text":"了許多。在整個家族遭到頂之淡時，他不流淚，没抱怨，只是平静地講述","box":[[47,734],[852,734],[852,754],[47,754]]},{"text":"自己的要求：“我只想回家看看，不知杨珍雲怎樣了，我很率她。現在","box":[[45,776],[854,776],[854,799],[45,799]]},{"text":"只能求助你了。”","box":[[43,820],[224,816],[224,840],[44,845]]},{"text":"我和力沙克是同事，俩人之間存在著朋友情義，古典小裹的“肝義","box":[[93,864],[853,865],[853,886],[93,885]]},{"text":"瞻”，在我身上立刻發酵，政治風被抛到腦後。他遭遇大，我不能不管。","box":[[44,907],[853,909],[853,930],[44,928]]},{"text":"這是上午姜振華找過我後，我思前想後打定的主意。我知道，力沙克每天關","box":[[44,950],[854,952],[854,975],[44,973]]},{"text":"押在黑除，没多少人理會，他若跑掉了，必會引起大的反響，後果可想而","box":[[44,994],[853,997],[853,1020],[44,1017]]},{"text":"知·因此，我整個下午在屋内反復思虑，確定了一個方案。我對力：“希","box":[[44,1039],[853,1040],[853,1061],[44,1060]]},{"text":"望你挺得住，這也是六月份你對我過的。我會你。雲媽媽那裹我也會","box":[[45,1082],[853,1085],[853,1106],[45,1103]]},{"text":"助。我已找到她，她很安全’你放心好了。”之後’我把整個“逃上海”的","box":[[44,1125],[854,1127],[854,1151],[44,1149]]},{"text":"方案告他，包括一些細節。我把他工作上的照片揭下乘，約定第二天晚","box":[[46,1170],[853,1173],[853,1194],[46,1191]]},{"text":"六時，在教師俱樂部北高梁地裹見面，我他備好一切。","box":[[45,1214],[666,1217],[666,1237],[45,1234]]},{"text":"我：“不是不相信梅老師和姜振華，了安全必謹慎。一會兒，我","box":[[92,1258],[855,1261],[855,1284],[92,1281]]},{"text":"要高聲申斥你，你也要向姜、梅抱怨我不肯忙·記住，明天下午六點，刮","box":[[45,1301],[855,1305],[855,1328],[45,1324]]},{"text":"了子，皮鞋擦凈，我你備一副手套。”","box":[[45,1345],[516,1344],[516,1368],[45,1369]]}],"dimensions":{"height":1451,"width":900}}