{"ocr_results":[{"text":"166","box":[[85,73],[116,73],[116,92],[85,92]]},{"text":"外交部文革紀實","box":[[628,70],[759,70],[759,90],[628,90]]},{"text":"57.西哈努克親王1967年9月12日講話，载於《1967年西哈努克講話》（金，情報","box":[[86,132],[759,132],[759,149],[86,149]]},{"text":"部，1968），真695。","box":[[123,162],[290,162],[290,182],[123,182]]},{"text":"58.参见Gurtov，见35，页350。","box":[[83,193],[370,192],[370,212],[83,213]]},{"text":"59.同上，真351。","box":[[86,226],[260,226],[260,243],[86,243]]},{"text":"60.群見杨赞暨：（中國留學生莫斯科红場流血記》，《百年潮》，1998年第3期，真","box":[[86,257],[758,257],[758,274],[86,274]]},{"text":"30-33；另見田木：（1.25红場事件始末），《環球文萃》，1996年1月28日。","box":[[123,289],[720,287],[720,304],[123,306]]},{"text":"61.杨赞臀，見上，页33。","box":[[86,320],[326,320],[326,337],[86,337]]},{"text":"62.田木，见65。","box":[[85,350],[253,350],[253,370],[85,370]]},{"text":"63.張锡昌：（中法篇一别具一格的建交方針），载於張锡昌等：《峰迭起一","box":[[84,382],[758,380],[758,400],[84,402]]},{"text":"共和國第三次建交高潮》（北京：世界知識出版社，1998），真5-86。","box":[[124,413],[676,414],[676,432],[124,431]]},{"text":"64.《中華人民共和國實錄》，见2，真392。","box":[[86,446],[460,446],[460,463],[86,463]]},{"text":"65.張锡昌，见主68，页87。","box":[[84,476],[328,475],[328,495],[84,496]]},{"text":"66.《人民日報》，1967年6月3日頭版。","box":[[84,507],[404,506],[405,526],[84,527]]},{"text":"67.司任：<文化大革命中的外交部奪權動一姚登山一席》，《炎黄春秋》，1993","box":[[84,538],[760,537],[760,557],[84,558]]},{"text":"年第11期，页66-67。","box":[[122,568],[299,571],[299,591],[122,588]]},{"text":"68.以上除注明出處者外，群见冉隆勃、馬继森：《周恩來與香港「六七暴動」内幕》","box":[[87,601],[756,601],[756,618],[87,618]]},{"text":"（香港：明報出版社有限公司，2001）。","box":[[126,633],[441,633],[441,650],[126,650]]},{"text":"69.童小鹏：《風雨四十年》（北京：中央文獻出版社，1996），真419420。","box":[[87,666],[693,666],[693,683],[87,683]]}],"dimensions":{"height":1313,"width":801}}