{"ocr_results":[{"text":"17.喬冠華的厄運和小姐調離外交部","box":[[25,46],[315,46],[315,63],[25,63]]},{"text":"347","box":[[670,48],[700,48],[700,67],[670,67]]},{"text":"用喬冠華當時的法是：「先利用大王八蛋解决小王八蛋的問题。」老翰","box":[[24,104],[697,106],[697,126],[24,124]]},{"text":"部們都同意，有的白己也寫了信通過江青轉毛，結果同喬、章的望相","box":[[24,140],[698,141],[698,161],[24,160]]},{"text":"反。毛澤束看到了章含之的信，批這是「借刀殺人」。毛何所指？語焉","box":[[23,175],[697,177],[697,197],[23,195]]},{"text":"不详。但是，這個「最高指示注定了喬、章的不幸。","box":[[25,212],[546,212],[546,232],[25,232]]},{"text":"喬冠華在劫難逃","box":[[255,295],[465,295],[465,316],[255,316]]},{"text":"當時正是四人帮大權在握之時，喬冠華在外交部已受到攻擎。5月下","box":[[67,350],[696,353],[696,373],[67,370]]},{"text":"旬一次中央會上，江青、張春橘指责喬在外交部不真批郢，應當對","box":[[24,385],[697,387],[697,407],[24,405]]},{"text":"部内「不團結負壹业做检查。","box":[[24,422],[302,423],[302,441],[24,440]]},{"text":"同年6月1日，尼泊爾國王访問成都和西藏，新任總理華國锋去成都","box":[[66,458],[696,459],[696,477],[66,476]]},{"text":"同國王會谈。外交部部長喬冠華和副部長韓念龍先到了成都。但他未到","box":[[22,494],[696,495],[696,513],[22,512]]},{"text":"機場迎接華國锋，也没有在賓館迎候，成為「對抗中央」、「蔑視中央领","box":[[23,528],[697,530],[697,549],[23,547]]},{"text":"導」的罪状·6月5日回到北京時，外交部已經贴满了批判他的大字報。","box":[[22,563],[694,565],[694,585],[22,583]]},{"text":"6门7日晚，中央政治局常委召開了有外交部問题的會，指责喬不真","box":[[22,600],[695,601],[695,619],[22,618]]},{"text":"抓批部，而是打内，青令他回去開會，做查。喬给毛當時的聯絡員","box":[[23,635],[694,636],[694,655],[23,653]]},{"text":"毛遠新打電話，毛遠新也喬「想利用中央來你打内」。7","box":[[22,668],[604,664],[604,691],[22,695]]},{"text":"7月28日唐山大地震，波及北京。29日外交部接到中央瓣公通知：","box":[[65,706],[692,707],[692,727],[65,726]]},{"text":"24小時内京束通縣可能發生7级以上大地震。外國驻華使领館集中在京束","box":[[21,741],[696,742],[696,762],[21,761]]},{"text":"地區，喬冠華立即指示组織外國驻華使领馆人員繁急撤離北京，確保他","box":[[23,778],[695,779],[695,797],[23,796]]},{"text":"們的平安。忙乎一天，24小時過去了。原來预報的大地震没有發生，喬","box":[[22,813],[697,814],[697,834],[22,833]]},{"text":"冠華又受到批，是|無組織無紀律的重錯」，是「在地震面前悍","box":[[23,849],[694,850],[694,868],[23,867]]},{"text":"失措的表現」，是「有失國家尊」。接著，外交部黛組開會批判喬冠華。","box":[[23,884],[693,885],[693,903],[23,902]]},{"text":"喬冠華寫讨。張春橘在讨上批：錯不是孤立的、偶然的，要同批","box":[[23,919],[695,921],[695,939],[23,937]]},{"text":"部聯繁起來。過了天，華國到外交部，部長喬冠華一無所知。這","box":[[23,955],[695,956],[695,974],[23,973]]},{"text":"時外交部已經有把喬拉下馬的大字報。8","box":[[18,987],[406,984],[407,1011],[18,1014]]},{"text":"1976年9月9日毛澤東逝世，10月6日王洪文、張春橘、江青和姚文元","box":[[66,1026],[695,1027],[695,1045],[66,1044]]},{"text":"四人被擒。中國政局劇變。10月17日喬冠華参加聯合國大會回到北","box":[[21,1060],[695,1061],[695,1081],[21,1080]]},{"text":"京，處境更加恶化，因為他被歸到四人一去了。外交部内大字報揭","box":[[21,1096],[695,1097],[695,1117],[21,1116]]},{"text":"發批判他「秉承四人意旨」把「按既定方針瓣]塞進他在聯合國大會做的","box":[[22,1131],[694,1133],[694,1152],[22,1150]]},{"text":"報告襄了。所谓「按既定方針瓣是毛澤東死後，9月中旬《人民口報》上刊","box":[[23,1167],[694,1169],[694,1187],[23,1185]]}],"dimensions":{"height":1313,"width":801}}