{"ocr_results":[{"text":"北大文革简史·第十三章文革中的周培源先生","box":[[348,94],[727,94],[727,111],[348,111]]},{"text":"呀，机要科呀，每科十几个人。我从我们科的队里，掉到后面，别的科","box":[[152,160],[927,160],[927,181],[152,181]]},{"text":"队伍里。","box":[[150,197],[235,197],[235,218],[150,218]]},{"text":"我们科长发现了，科长叫邢永宁。特负责，说，不行。当时他27岁，","box":[[193,233],[928,234],[928,257],[193,256]]},{"text":"后来当副参谋长。我是十六岁，他说，掉队不行。找他，他是科长，有","box":[[150,273],[927,273],[927,293],[150,293]]},{"text":"一匹马。负责管他马的同志，大家管他叫马夫。他拉着科长的马，到后","box":[[151,311],[927,311],[927,331],[151,331]]},{"text":"面，让我坐上马，赶上部队。那时候官兵关系多好哇，他不批评你，就","box":[[150,347],[927,346],[927,367],[150,368]]},{"text":"是用行动帮助你。","box":[[150,385],[335,385],[335,406],[150,406]]},{"text":"每天都行军，每天都打仗。因为我们是指挥机关，不是战斗部队，拿","box":[[193,421],[928,421],[928,444],[193,444]]},{"text":"枪去和敌人拼，而是指挥，这个战怎么怎么打。","box":[[149,460],[658,460],[658,480],[149,480]]},{"text":"那时候是二纵队，62军，下面分旅，旅下面分团。","box":[[196,498],[733,498],[733,518],[196,518]]},{"text":"一到地方，部队休息了。我们开始、翻译电报，或者发电报，发给各","box":[[195,535],[927,535],[927,555],[195,555]]},{"text":"单位，或者收电报。收电报马上给首长送过去，怕耽搁敌情：战场情况","box":[[149,569],[927,570],[927,593],[149,592]]},{"text":"很复杂，瞬息万变。","box":[[150,610],[362,610],[362,631],[150,631]]},{"text":"也有不成功的事情，1947年，我们有个同志叫做张锋，年纪比我大，","box":[[193,644],[928,646],[928,669],[193,667]]},{"text":"人是特好，他反应慢。一个电报，我们都发完了，他没发，还半截儿呐。","box":[[150,685],[927,685],[927,706],[150,706]]},{"text":"部队行军了，行军中没法翻译。走啊走啊，走了一夜到地方。部队住下","box":[[149,720],[927,722],[927,745],[149,743]]},{"text":"了，他管的那个部队来电报了，请示任务。一看，着急了：因为迟发一","box":[[152,759],[929,758],[929,781],[152,782]]},{"text":"个电报，整个这师的部队，两天的路，变成一天走。就这么严重。","box":[[149,794],[861,795],[861,819],[149,818]]},{"text":"那个时候就特紧张：翻译电报一点儿都不能错，一点儿不能耽误，所","box":[[195,834],[927,835],[927,856],[195,855]]},{"text":"以特别累。经常是白天行军，晚上译电报。晚上行军，白天译电报。部","box":[[151,870],[929,871],[929,894],[151,893]]},{"text":"队正在打仗，一样的事情，领导也不能休息。战争年代特苦，特辛苦。","box":[[152,910],[915,910],[915,931],[152,931]]},{"text":"有的时候走着走着就睡着了，啪，就摔倒了，睡着了。","box":[[150,946],[734,947],[734,968],[150,967]]},{"text":"我觉得这些故事，回忆起来，比较好的，就是罗瑞卿，给我的印象非","box":[[194,984],[926,985],[926,1006],[194,1005]]},{"text":"常深刻。","box":[[152,1022],[234,1022],[234,1041],[152,1041]]},{"text":"那是1948年，蠡泗战役以后，我们机要科党小组开会。罗瑞卿当时","box":[[196,1061],[927,1061],[927,1081],[196,1081]]},{"text":"是我们的政委，他就参加我们党小组会。我们每个人都得检讨工作，翻","box":[[149,1096],[928,1097],[928,1118],[149,1117]]},{"text":"译电报太慢啦，有的时候耽误啦。他说，哎呀，某处某处打得不好，有","box":[[149,1135],[927,1135],[927,1156],[149,1156]]},{"text":"什么毛病、什么毛病。他给我们党小组会上，那么大一个官儿，一样做","box":[[149,1171],[928,1172],[928,1193],[149,1192]]},{"text":"自我批评。","box":[[152,1208],[260,1210],[260,1231],[152,1229]]},{"text":"他给我的印象特好，后来文化大革命，有人批评我：你跟罗瑞卿打过","box":[[193,1244],[928,1245],[928,1269],[193,1268]]},{"text":"乒乓球，之类的。","box":[[148,1284],[334,1285],[334,1306],[148,1305]]},{"text":"那时候，首长们对于小干部们、士兵们，没有什么官架子。不象现在，","box":[[194,1320],[928,1321],[928,1344],[194,1343]]},{"text":"当官的不得了啦。那时候他们都非常平易近人。我还有个例子：进军大","box":[[152,1361],[926,1361],[926,1381],[152,1381]]},{"text":"1439","box":[[889,1421],[929,1421],[929,1443],[889,1443]]}],"dimensions":{"height":1518,"width":1075}}