{"ocr_results":[{"text":"北大文革简史·第四章工作组存废，最高层翻手为云覆手为雨","box":[[283,94],[792,94],[792,111],[283,111]]},{"text":"“北大没有个党委代替，撤工作组我不赞成。”一直保持沉默的邓小","box":[[207,158],[928,158],[928,183],[207,183]]},{"text":"平霍地一下站起来，一手叉腰，一手指着陈伯达，当即表示反对说：“我","box":[[151,198],[928,197],[928,218],[151,219]]},{"text":"们要讲得客观一些，要了解第一线的困难。什么叫放手？！要不要政策？！","box":[[150,236],[928,236],[928,256],[150,256]]},{"text":"我们不行，你们上去。你们那样行，我们统统撤出来。党委垮了，工作","box":[[151,274],[927,274],[927,294],[151,294]]},{"text":"组没有了，党的领导在哪里？谁来放手发动？你们根本没有搞过群众运","box":[[148,309],[928,310],[928,333],[148,332]]},{"text":"动，你们去试试看！”","box":[[147,346],[387,342],[387,369],[148,374]]},{"text":"他又说：“要教会工作组做工作。有的学校没有工作队恐怕不行。”","box":[[192,384],[928,380],[928,408],[192,411]]},{"text":"刘少奇也讲：“多数工作组是好的，还是帮助教育，改正错误。赶工","box":[[195,423],[928,423],[928,443],[195,443]]},{"text":"作组，有的不应该赶。”“现在工作组还是要的。实在不行的，撤了。","box":[[150,458],[916,458],[916,482],[150,482]]},{"text":"撤了还要换，因为没有其他力量领导。”代表军队参加会议的叶剑英、","box":[[149,497],[914,497],[914,520],[149,520]]},{"text":"刘志坚也明确反对撤工作组。","box":[[149,535],[457,535],[457,555],[149,555]]},{"text":"这个会议没有设专人记录。会议进行过程中，江青手脚进来了，","box":[[193,572],[926,573],[926,594],[193,593]]},{"text":"在靠着记录席外边的沙发上坐下，把手里的包放在沙发上。她没有和主","box":[[150,612],[928,612],[928,632],[150,632]]},{"text":"持会议的刘少奇打招呼。江青看到了争吵的场面。她没有记录，只是听。","box":[[149,647],[928,648],[928,669],[149,668]]},{"text":"这天晚上，毛泽东约见各大区书记和“中央文革小组”成员。此时，","box":[[195,686],[927,686],[927,707],[195,707]]},{"text":"他已决定召开党的十一中全会，把“文化大革命”以党的决议形式正式","box":[[151,724],[928,724],[928,744],[151,744]]},{"text":"确定下来。为此，他指示陶铸在文革小组起草的《无产阶级文化大革命","box":[[150,761],[927,761],[927,781],[150,781]]},{"text":"的形势和党的若干方针问题》基础上，主持起草《中国共产党中央委员","box":[[151,798],[926,798],[926,819],[151,819]]},{"text":"会关于无产阶级文化革命的决定》。他召集来各大区书记，就是要同他","box":[[150,837],[926,837],[926,857],[150,857]]},{"text":"们一起讨论这个《决定》，做他们的工作，统一思想。毛泽东说：","box":[[150,873],[858,873],[858,893],[150,893]]},{"text":"“今天各大区的书记和文革小组的成员都到了，会议的任务是搞好文","box":[[206,908],[928,910],[928,934],[205,932]]},{"text":"件。主要是改变派工作组的作法，由学校革命师生及中间状态的一些人","box":[[150,949],[926,949],[926,969],[150,969]]},{"text":"组成学校文化革命小组来领导文化大革命。学校的事只有他们懂得，工","box":[[149,986],[928,986],[928,1006],[149,1006]]},{"text":"作组不懂。有些工作组搞了些乱事。学校文化大革命无非是斗和改，工","box":[[150,1023],[927,1023],[927,1044],[150,1044]]},{"text":"作组起了阻碍运动的作用，我们能斗能改吗？象伯赞写了那么多书，","box":[[151,1062],[916,1062],[916,1082],[151,1082]]},{"text":"你还没有读，怎么斗？怎么改？学校的事，‘庙小神灵大，池浅王八多”，","box":[[149,1096],[926,1095],[926,1118],[149,1119]]},{"text":"所以要依靠学校内部的力量，工作组是不行的。我也不行，你也不行，","box":[[151,1135],[916,1135],[916,1156],[151,1156]]},{"text":"省委也不行。要斗要改都得依靠本校、本单位，不能依靠工作组。工作","box":[[150,1174],[927,1174],[927,1194],[150,1194]]},{"text":"组能否改成为联络员？改成顾问权力太大，或者叫观察员。工作组阻碍","box":[[150,1211],[927,1211],[927,1231],[150,1231]]},{"text":"革命，也有不阻碍革命的。工作组阻碍革命势必变成反革命。西安交大","box":[[150,1249],[928,1249],[928,1269],[150,1269]]},{"text":"不让人家打电话，不让人家派人到中央，为什么怕人到中央？让他们来","box":[[150,1287],[928,1287],[928,1307],[150,1307]]},{"text":"包围国务院。文件要写上，可以打电话，也可以派人。那样怕能行吗？","box":[[151,1323],[915,1323],[915,1343],[151,1343]]},{"text":"所以西安、南京报馆被围三天，吓得魂不附体，就那么怕？你们这些人","box":[[151,1362],[927,1362],[927,1382],[151,1382]]},{"text":"384","box":[[146,1422],[177,1422],[177,1442],[146,1442]]}],"dimensions":{"height":1518,"width":1075}}