{"ocr_results":[{"text":"北大文革简史·第五章北大的“红卫兵运动”","box":[[348,93],[720,93],[720,110],[348,110]]},{"text":"“那不叫游泳，那叫闲庭信步。”这时毛泽东边作出闲庭信步的样子","box":[[209,159],[928,159],[928,183],[209,183]]},{"text":"边说：“你要能这样，就从必然王国到自由王国了。你们老怕别人批评。","box":[[149,198],[927,198],[927,218],[149,218]]},{"text":"马克思主义就是压出来的。经风雨，发展兴旺起来。”","box":[[148,233],[738,230],[738,257],[148,260]]},{"text":"江青说：“不能让她老出风头，要让她谦虚。”","box":[[192,270],[705,266],[706,295],[192,298]]},{"text":"毛泽东说：“你怎么能这样说呢？要让人家干革命嘛！”","box":[[192,308],[804,303],[804,333],[192,338]]},{"text":"记者不失时机地拍下了毛泽东“闲庭信步”的照片。","box":[[195,348],[752,348],[752,368],[195,368]]},{"text":"随后，游行开始了，游行队伍像奔腾不息的河流一样浩浩荡荡地通过","box":[[195,387],[928,387],[928,407],[195,407]]},{"text":"大安门城楼。徐雅雅是北京市戏剧专科学校的红卫兵，这大，她组织北","box":[[151,425],[926,425],[926,442],[151,442]]},{"text":"京市戏剧专科学校的红卫兵们唱着歌，打着竹板，列着方阵通过天安门","box":[[150,461],[928,461],[928,481],[150,481]]},{"text":"广场。他们穿着旧军装，腰间扎着皮带，头上戴着军帽。行进的过程中，","box":[[149,499],[927,499],[927,519],[149,519]]},{"text":"他们一边唱歌，一边用竹板打出“啪啪”响的节奏，特别神气威风，也","box":[[149,535],[927,536],[927,557],[149,556]]},{"text":"特别引人注目。","box":[[149,573],[310,573],[310,594],[149,594]]},{"text":"毛泽东俯视着城下的游行队伍，兴奋地对站在旁边的林彪说：“这个","box":[[195,610],[928,610],[928,633],[195,633]]},{"text":"运动规模很大，确实把群众发动起来了，对全国人民的思想革命化有很","box":[[148,647],[927,648],[927,669],[148,668]]},{"text":"大的意义。”","box":[[148,686],[287,681],[288,705],[149,710]]},{"text":"周恩来对毛泽东说：“主席，一些北京的学生说，外地大中学校的同","box":[[195,724],[927,724],[927,744],[195,744]]},{"text":"学纷纷来到首都，是不是会影响首都各学校的教育改革？人来多了，食","box":[[149,759],[929,760],[929,783],[149,782]]},{"text":"宿、交通都有困难，9月份以前学校复课恐怕不易实现。”","box":[[146,795],[784,792],[785,820],[146,823]]},{"text":"毛泽东回答说：“不要紧，群众目前只是刚刚发动起来，搞革命就是","box":[[195,835],[928,835],[928,858],[195,858]]},{"text":"要搞串连，大革命就要串连，恩来，我们年轻的时候，不是就靠串连才","box":[[151,873],[927,873],[927,893],[151,893]]},{"text":"搞到一起吗？北洋军阀虽然有枪有炮，可是全国的学生团结起来，他们","box":[[150,911],[927,911],[927,932],[150,932]]},{"text":"就没有办法。”","box":[[149,948],[312,944],[312,969],[150,973]]},{"text":"周恩来应诺道：“那好，我去安排一下。”","box":[[192,983],[655,980],[655,1007],[192,1010]]},{"text":"刘少奇远远地站在天安门城楼东边，不言不语。他看见伍修权，两人","box":[[195,1023],[926,1023],[926,1044],[195,1044]]},{"text":"聊了一会儿，刘少奇说：“北大聂元梓的大字报我反复地看了几遍，实","box":[[150,1060],[928,1060],[928,1083],[150,1083]]},{"text":"在看不出它的意义为什么比巴黎公社宣言还要大。”","box":[[148,1095],[711,1092],[711,1119],[148,1122]]},{"text":"毛泽东走到刘少奇身边，两人侃侃而谈。从远处看过去，他们就像朋","box":[[196,1136],[927,1136],[927,1157],[196,1157]]},{"text":"友间的谈心，更像师生的交流。主要是毛泽东说，刘少奇听。说的耐心","box":[[150,1174],[927,1174],[927,1194],[150,1194]]},{"text":"而诚恳；听的虚心而谦卑。毛泽东说：“中央犯了这么大的错误，总得","box":[[150,1211],[928,1209],[928,1231],[150,1233]]},{"text":"有人出来承担责任。你回去要同光美同志和孩子们讲清楚，不要因此而","box":[[150,1249],[927,1249],[927,1269],[150,1269]]},{"text":"背包袱。”","box":[[148,1285],[261,1282],[262,1306],[149,1309]]},{"text":"在离毛泽东不远处，康生看见一个红卫兵代表站在身后，便问他：“你","box":[[195,1323],[927,1323],[927,1343],[195,1343]]},{"text":"是哪个学校的呀？”【笔者注：这可能是“文革”中“揪叛徒”的滥觞。当然，","box":[[150,1360],[927,1360],[927,1383],[150,1383]]},{"text":"433","box":[[898,1422],[928,1422],[928,1442],[898,1442]]}],"dimensions":{"height":1518,"width":1075}}