{"ocr_results":[{"text":"也受到了迫害。然而制造这个迫害大惨案的干将是些什么人呢？地委付书记卜虹云，地主家庭","box":[[168,193],[1060,194],[1060,214],[168,213]]},{"text":"出身，其父被我们镇压，抗日战争时是个大叛徒，文化大革命中是黑省委的特务头目之一。地","box":[[168,234],[1061,236],[1061,256],[168,254]]},{"text":"委付书记兼专员谢子和，富农家庭出身，美帝教会学校学生，当过防共团团长，是个反共老手。","box":[[169,279],[1061,279],[1061,296],[169,296]]},{"text":"地监委书记王荣，是个变质分子，吃、喝、娉、赌、抽的大流氓，是镇压革命同志的剑子手，","box":[[168,320],[1050,320],[1050,340],[168,340]]},{"text":"他亲手镇压革命群众数以千计，实属“大阎君”。地委付书记苗枫，原名苗思吉，大地主家庭，","box":[[167,360],[1059,361],[1059,381],[167,380]]},{"text":"防共团团长，阎匪区长，杀死共产党员数人，是屠杀共老手。由此可见，晋中十月事件确实是","box":[[169,405],[1058,405],[1058,422],[169,422]]},{"text":"一场资产阶级复辟和无产阶级反复辟的阶级斗争。任、王、张，这是杀出来的革命领导干部。","box":[[167,443],[1051,444],[1051,465],[167,464]]},{"text":"任井夫同志，贫农出身，原任过地委委员、常务付专员、平遥县委第一书记。王振国同志，贫","box":[[169,487],[1059,487],[1059,504],[169,504]]},{"text":"农出身，担任过地委付秘书长、文水县委书记。张怀英同志，贫农出身，原是昔阳县委书记、","box":[[170,529],[1049,529],[1049,546],[170,546]]},{"text":"后任文水县委书记。文化革命开始先后，这三个同志给毛主席和江青同志三次写信揭发黑省委","box":[[169,571],[1060,571],[1060,588],[169,588]]},{"text":"和黑地委的罪恶。等混蛋们，怕任、王、张继续揭露他们的罪行，于是在华北局会议上密谋策","box":[[168,611],[1060,611],[1060,631],[168,631]]},{"text":"划，定了调子，列了名单重新大搞什么“晋中的三家村”。生事捏非，横加罪名，泡制了小册子，","box":[[168,652],[1061,654],[1061,674],[168,672]]},{"text":"印发全省各地，大造反革命舆论。华北局会议，一面指使道德败坏、腐化透顶的忠实走卒黑地","box":[[169,697],[1060,697],[1060,714],[169,714]]},{"text":"委宣传部长刘松青，泡制重新镇压任、王、张等同志的大字报。另一面亲自出面，大小会议点","box":[[169,737],[1059,737],[1059,754],[169,754]]},{"text":"名，同时派大叛徒卫逢棋到文水县，大会子手王荣到平遥县坐镇指挥。同时煽动不明真相的干","box":[[168,777],[1060,778],[1060,798],[168,797]]},{"text":"部和群众，去劳改队唆使劳教队折磨任井夫，烂脚跟，骨格变形，还把张怀英从医院的床上揪","box":[[170,821],[1060,821],[1060,838],[170,838]]},{"text":"回文水，用七种刑法，打得死去三次，企图把这些革命同志，置于死地而后快。雾云遮不住太","box":[[169,861],[1059,861],[1059,881],[169,881]]},{"text":"阳。去年冬季至今年春季，这三个同志在江青同志指示、广大革命群众的帮助下，他们杀将回","box":[[169,903],[1059,903],[1059,923],[169,923]]},{"text":"晋中，六次揭发黑地委问题和革命左派搞文化大革命，现在是中共晋中核心小组成员。然而，","box":[[168,945],[1049,945],[1049,965],[168,965]]},{"text":"就这样的革命领导十部，却有人用当年整任王张的材料，用当年整任、王、张的人马，用当年","box":[[168,988],[1059,988],[1059,1005],[168,1005]]},{"text":"整任、王、张的办法，依占势力、蒙蔽群众，掀起全区性的一股反革命复辟逆流围攻斗争，炮","box":[[170,1029],[1061,1029],[1061,1046],[170,1046]]},{"text":"轰火烧，反动气焰十分嚣涨。","box":[[167,1068],[438,1069],[437,1090],[167,1089]]},{"text":"极左派的阶级斗争观点也挺有意思，除了任、王、张以外，当时山西省和晋中地区的共产","box":[[211,1110],[1060,1109],[1060,1130],[211,1131]]},{"text":"党的高级干部都儿乎成为了地主恶霸出身的十恶不赦的大坏蛋！","box":[[169,1154],[765,1154],[765,1171],[169,1171]]},{"text":"晋中“十月事件”很复杂，体制内和体制外有多种不同的看法。","box":[[213,1196],[808,1196],[808,1213],[213,1213]]},{"text":"从现在的眼光看，毛泽东倡导的大跃进本来就不对，后任的昔阳县委书记张润槐“纠大跃","box":[[213,1236],[1061,1236],[1061,1256],[213,1256]]},{"text":"进之偏”当然是正确的。张润槐是第一个“反大寨”（如果他是有意的话）的人，或者是第一个","box":[[168,1278],[1060,1278],[1060,1298],[168,1298]]},{"text":"“被反大寨”（如果他是无意的，而被陈永贵“诬陷”的话）的人。虽然大寨那时还没有那么红，","box":[[175,1318],[1058,1318],[1058,1338],[175,1338]]},{"text":"但被陈永贵和大寨人记了仇，在后来的文革中张润槐被大寨人批斗的“灵魂出窍”。其实，在那","box":[[169,1362],[1060,1362],[1060,1379],[169,1379]]},{"text":"个全党“昏头”、全国“虚报”的年代，大寨虚报点土地（没有虚报粮食总产量，因为土地数量","box":[[170,1404],[1060,1404],[1060,1421],[170,1421]]},{"text":"不同，造成了亩产量的不同）也没什么，要追究应该先追究中央、省、市、地的政策和路线的","box":[[169,1446],[1059,1446],[1059,1463],[169,1463]]},{"text":"问题，真是没有必要追究大寨的这些小问题，而是应该帮助大寨逐渐改止问题。","box":[[169,1487],[917,1487],[917,1504],[169,1504]]},{"text":"从民主的角度看，昔阳县委的选举是符合《党章》原则的，而普中地委和张润槐的作法是","box":[[213,1528],[1061,1528],[1061,1548],[213,1548]]},{"text":"157","box":[[1034,1630],[1064,1630],[1064,1650],[1034,1650]]}],"dimensions":{"height":1754,"width":1241}}