{"ocr_results":[{"text":"持的造反派中的打砸抢分子、指挥武斗造成严重后果的头头；抵制大寨极左错误；批了极左；","box":[[168,194],[1048,194],[1048,214],[168,214]]},{"text":"炮制了《三上桃峰》，替刘少奇翻案。这些行为得罪了“四人帮”，以至于江青亲自穿上军装“炮","box":[[168,235],[1060,235],[1060,255],[168,255]]},{"text":"轰谢振华”。由于当时“四人帮”不能公开直接地批判周恩来，只能间接地借“批林批孔”和批","box":[[168,279],[1061,279],[1061,296],[168,296]]},{"text":"下面的人来批周，所以谢振华在一定程度上是替周恩来“顶了杠子”。王谦在粉碎“四人帮”一","box":[[171,320],[1058,320],[1058,337],[171,337]]},{"text":"年半之后，还要大唱“阶级斗争”、“路线斗争”的高调，借清查“四人帮”之际，继续揭批谢","box":[[169,362],[1060,362],[1060,379],[169,379]]},{"text":"振华的反“四人帮”的问题，不能不说王谦是冥顽不化的“四人帮”集团的骨干分子。","box":[[168,403],[985,403],[985,423],[168,423]]},{"text":"当然，王谦自立“清查”标准有其自身的利益在内。如果真止地清查“四人帮”，岂不清查","box":[[214,446],[1060,446],[1060,463],[214,463]]},{"text":"了自己？一个省委第一书记不讲大是大非，置公平与正义于不顾，这种人还有资格当省委第一","box":[[169,485],[1062,485],[1062,505],[169,505]]},{"text":"书记吗？正是有了王谦这样的人，山西省非但没有扭转文革中的整人的纷乱局面，反而又制造","box":[[170,528],[1059,528],[1059,545],[170,545]]},{"text":"了很多很多的冤案。由于冤案很多，这里只能挑选儿个典型的案例来叙述。","box":[[171,571],[875,571],[875,588],[171,588]]},{"text":"2“反大寨”冤案就很多","box":[[221,606],[541,606],[541,629],[221,629]]},{"text":"李顺达冤案","box":[[217,651],[338,651],[338,672],[217,672]]},{"text":"李顺达，山西平顺县人。平顺县与河南林县（林州）、河北涉县毗邻，都是一个贫困山区。","box":[[212,695],[1060,695],[1060,715],[212,715]]},{"text":"平顺又是一个革命老区，解放的早，所以虽然贫穷，这里的人民觉悟高，解放前几年和解放初","box":[[169,734],[1060,734],[1060,754],[169,754]]},{"text":"期就涌现了许多劳动模范。现在的平顺县也就是十六万人，解放初期可能不到十万人，一个小","box":[[168,777],[1061,777],[1061,797],[168,797]]},{"text":"小的平顺县，著名的全国劳模就有李顺达、郭玉恩、武侯梨、申纪兰等，李顺达和申纪兰还是","box":[[170,821],[1060,821],[1060,838],[170,838]]},{"text":"一个村子的人，应该是山西省劳模最集中的地方。这些劳模在支援前线、农业合作化运动、人","box":[[169,862],[1058,862],[1058,879],[169,879]]},{"text":"民公社运动中都起到了带头作用。这些人最大的特点就是“实在”、实干，不善于说谎，这也是","box":[[169,904],[1061,904],[1061,921],[169,921]]},{"text":"这批劳模没有在大跃进中再度辉煌的原因。在文革前，以平顺县为主的晋东南劳模代表团曾经","box":[[168,946],[1061,946],[1061,963],[168,963]]},{"text":"访问大寨，这些“老农民”很有经验，对大寨的粮食产量问题提出了质疑，对大寨“虚报产量”","box":[[169,988],[1062,988],[1062,1005],[169,1005]]},{"text":"就不太服气。文革中，李顺达虽然与陈永贵、解悦共同创建了一个群众组织，但合作了没几天，","box":[[168,1027],[1059,1027],[1059,1047],[168,1047]]},{"text":"终因看不惯陈永贵翻脸不认人（即不认培养过他的山西省委和普中地委）的造反派的行为和反","box":[[168,1071],[1060,1071],[1060,1088],[168,1088]]},{"text":"对解放军的行为而分道扬了。李顺达和他的西沟也成为了山西反中央文革派，抵制、对抗大","box":[[168,1110],[1062,1110],[1062,1130],[168,1130]]},{"text":"寨的一面旗帜。之后，李顺达一直与军队站在一起，抵制中央文革在山西势力的“篡党夺权”","box":[[169,1154],[1051,1154],[1051,1171],[169,1171]]},{"text":"行为。","box":[[167,1194],[220,1194],[220,1215],[167,1215]]},{"text":"粉碎“四人帮”之后，由于陈永贵、王谦为代表的“四人帮”势力还把持着山西的政权，","box":[[212,1236],[1047,1236],[1047,1256],[212,1256]]},{"text":"李顺达成为了清查“四人帮”的对象。李顺达被打成了“山西反大寨的总代表”、“晋东南“四","box":[[169,1278],[1060,1278],[1060,1298],[169,1298]]},{"text":"人帮”篡党夺权的罪魁祸首”，还搞了一个“李顺达帮派体系”，牵连了数百人。在清查李顺达","box":[[168,1319],[1061,1319],[1061,1339],[168,1339]]},{"text":"时，清查负责人对李顺达说：“只要你做个检查，就选你当代表（指党的‘十一大’代表）。”李","box":[[168,1362],[1062,1362],[1062,1379],[168,1379]]},{"text":"顺达说：“代表可以不当，但我没做过的事，不能瞎说。我瞎说了，不就是欺骗党欺骗人民吗？！”","box":[[167,1402],[1064,1401],[1064,1421],[167,1422]]},{"text":"此后，李顺达被免除了省委常委、普东南地委书记等职务，并因此使他的“十一大”代表资格","box":[[168,1446],[1059,1446],[1059,1463],[168,1463]]},{"text":"落选。","box":[[166,1485],[221,1485],[221,1506],[166,1506]]},{"text":"因为李顺达对大寨的作法不满，就说李顺达“反大寨”，；说李顺达是“晋东南“四人帮","box":[[212,1528],[1046,1528],[1046,1548],[212,1548]]},{"text":"451","box":[[1035,1630],[1063,1630],[1063,1650],[1035,1650]]}],"dimensions":{"height":1754,"width":1241}}