{"ocr_results":[{"text":"已杀地富便返回家。8月27日上午，郑逢姣在郑开德家主持召开了生产队以上干部会，会","box":[[191,144],[1052,144],[1052,164],[191,164]]},{"text":"上说：“前三批杀得很好，这次我回来，也要杀一批…”并点名要各队报名单，后决定杀","box":[[189,174],[1051,176],[1051,195],[189,194]]},{"text":"七人。当天下午，郑逢姣指挥将郑际东等七名地富分子及子弟用绳子勒死（是命令一些没被","box":[[190,208],[1051,208],[1051,228],[190,228]]},{"text":"杀的地富子弟勒的)。","box":[[190,240],[383,240],[383,260],[190,260]]},{"text":"同年9月14日，郑逢姣在郑开德家主持召开大队支委会，并在会上说：“要大家来是商","box":[[234,273],[1052,273],[1052,293],[234,293]]},{"text":"量一下，是不是再杀一批··”会议当中，杨家公社主任彭心明、公安员樊书守等三人来到","box":[[189,305],[1052,305],[1052,325],[189,325]]},{"text":"会场，郑逢姣将开会内容告知三人后，樊书守提出：“九五命令①早下了，杀人问题影响很","box":[[191,340],[1050,340],[1050,357],[191,357]]},{"text":"大，不能再杀了。”郑逢姣不听劝阻，并说：“我们大队四类分子这样多，又这么坏，不准杀","box":[[190,372],[1050,372],[1050,389],[190,389]]},{"text":"也要杀。”由于部分大队干部支持郑逢姣，彭心明无奈说：“我的先生·你们要搞就搞远点，","box":[[191,405],[1047,405],[1047,422],[191,422]]},{"text":"搞到宁远界子边去，免得影响我们公社。”","box":[[190,437],[582,437],[582,454],[190,454]]},{"text":"当大下午，郑逢姣组织召开了生产队以上干部会，在会上重复了在支委会的讲话内容，并分","box":[[192,470],[1049,470],[1049,487],[192,487]]},{"text":"任务到各队。次日，郑逢姣指挥民兵，将19名地富及子女押至宁远欧冲垒山里杀害②。","box":[[191,502],[1013,502],[1013,519],[191,519]]},{"text":"我们来到了这个被称为作喜鹊郑家的小山村。该大队文革中先后杀了37人，是道县杀人事","box":[[190,567],[1051,567],[1051,584],[190,584]]},{"text":"件真正的爆发点。几十百把栋破破烂烂的砖房，成一大两小三个块，分布在一个山洞③里，","box":[[189,598],[1051,598],[1051,618],[189,618]]},{"text":"背靠看一片平缓的红土丘陵。山上原来尽是合抱粗的大树，58年人民公社化办食堂搞大兵","box":[[190,632],[1050,632],[1050,649],[190,649]]},{"text":"团作战的时候，都砍下来炼了（废）铁。现在只剩些低矮的權木和丈把高的马尾松。交通不","box":[[191,665],[1051,665],[1051,682],[191,682]]},{"text":"甚便利，村民生活一直比较困难。现任支书郑逢桥要杀鸡置酒款待我们，被我们坚辞了。提","box":[[191,697],[1051,697],[1051,714],[191,714]]},{"text":"起钟佩英，郑支书说：“那是一个很体面的女人家，那时大约四十多岁，念过书，粗活细活","box":[[191,730],[1051,730],[1051,747],[191,747]]},{"text":"都拿得起，还会做衣裳。听说是蓝山那边一家大户人家的女，解放初期跑到贵州，和我们大","box":[[191,762],[1050,762],[1050,779],[191,779]]},{"text":"队在那里做事的郑元君结了婚。六五年清理阶级队伍时遣送回来的。”问起郑元君什么成份，","box":[[191,795],[1050,795],[1050,812],[191,812]]},{"text":"有何劣迹，他说：“郑元君土改时没定成份。他一直在外面做事，在乡里没听说有劣迹。只","box":[[190,827],[1049,827],[1049,844],[190,844]]},{"text":"是他的堂兄郑元赞④，1952年为首组织一伙土匪在宁远搞了个三·二九暴动，杀了我们一","box":[[188,858],[1051,859],[1051,879],[188,877]]},{"text":"个县委组织部长和两名干部。参加暴动的人基本上都镇压了，只有郑元赞跑脱了，听说跑到","box":[[188,889],[1052,890],[1052,910],[188,909]]},{"text":"了台湾。这些事情，我们也是听说的，搞不太清楚。”","box":[[191,923],[693,923],[693,943],[191,943]]},{"text":"“郑元赞的事与郑元君、钟佩英有什么关系吗？是不是郑元君参加了宁远暴动？”","box":[[196,953],[965,952],[965,975],[196,976]]},{"text":"“郑元君倒没听说参加了宁远暴动。他是64年社教时揪出来的，戴着历史反革命分子的帽","box":[[197,987],[1051,988],[1051,1008],[197,1007]]},{"text":"子遣送回来的，原来在贵州一个仓库里当保管员。65年在衡州（衡阳市）撞汽车自杀了。”","box":[[190,1020],[1046,1019],[1046,1039],[190,1040]]},{"text":"“这么说钟佩英本人并没有定为‘四类分子”，当时杀人时，队上那么多四类分子，为什么","box":[[196,1052],[1050,1053],[1050,1073],[196,1072]]},{"text":"首选她呢？”","box":[[190,1085],[310,1085],[310,1105],[190,1105]]},{"text":"郑支书说：“喉，那阵子，钟佩英有了这层社会关系，老老实实呆在屋里，也难保没事。她","box":[[190,1120],[1050,1120],[1050,1137],[190,1137]]},{"text":"又去参加什么“湘江风雷”，搞反革命串联，我那时是支委，那天开会，他们讲起钟佩英的","box":[[190,1151],[1051,1151],[1051,1171],[190,1171]]},{"text":"事，我大吃一惊，钟佩英搞了这么多活动，我怎么一点都不知道？不过死也死得惨，就在你","box":[[189,1183],[1052,1184],[1052,1204],[189,1203]]},{"text":"们过路的那口山塘边，好几天没收尸。”","box":[[190,1215],[558,1215],[558,1234],[190,1234]]},{"text":"“要杀她，就是因为她参加了‘湘江风雷’？没有别的原因？”不知道为什么，我总觉得杀","box":[[195,1247],[1051,1248],[1051,1268],[195,1267]]},{"text":"钟佩英的事，不会这么简单。5","box":[[191,1281],[490,1281],[490,1298],[191,1298]]},{"text":"一块大石头，叫他永世不得翻身。","box":[[190,1345],[454,1345],[454,1362],[190,1362]]},{"text":"①1967年9月5日，中共中央、国务院、中央军委、中央文革小组发布《关于不准抢夺人民解放军武器、","box":[[186,1364],[1042,1367],[1042,1390],[186,1387]]},{"text":"装备和各种军用物资的命令》，史称9.5命令。这里所说的九.五命令是指47军6950部队针对道县杀人事件，","box":[[187,1391],[1049,1392],[1049,1412],[187,1411]]},{"text":"结合宣传中央9.5命令发出的严禁杀人的命令。","box":[[189,1418],[564,1418],[564,1435],[189,1435]]},{"text":"②这19人大多是婆婆姥姥和未成年的孩子，其中有两个60多岁的瞎眼婆婆和两个10岁以下的小孩，他们","box":[[186,1439],[1052,1441],[1052,1461],[186,1459]]},{"text":"是在宁远欧冲垒路边的荒坡上被活理的。因为理人挖了四个大坑，现在那里得了个新地名“四个坑”。","box":[[190,1467],[1011,1467],[1011,1484],[190,1484]]},{"text":"③洞：应为，四周是山的由地。在道县一律写作“洞”。","box":[[189,1492],[653,1492],[653,1509],[189,1509]]},{"text":"?郑元赞，道县四马桥区杨家乡郑家村人，1948年曾任国民政府道县伪县长，1949年任国民政府宁远县伪","box":[[186,1511],[1052,1513],[1052,1536],[186,1534]]},{"text":"县长，1952年为首在宁远县组织3.29暴动，暴动被镇压后，经香港逃到台湾，后死于台湾。","box":[[191,1540],[934,1540],[934,1557],[191,1557]]},{"text":"有人说钟佩英参加“湘江风雷”根本没有那回事，被杀是因为大队上有人打她的主意，遭到拒绝，怀恨","box":[[186,1560],[1049,1562],[1049,1585],[186,1582]]},{"text":"在心，借机杀人。但一家之说，缺乏证据支持。","box":[[190,1588],[571,1588],[571,1605],[190,1605]]},{"text":"41","box":[[609,1611],[630,1611],[630,1628],[609,1628]]}],"dimensions":{"height":1755,"width":1241}}